potatoscript/potatoPostgreSQL.py
potatoscript/test.py
python/potatoPostgreSQL.py
python/pyPostgreSQL.py
python/xPostgreSQL.py
xPostgreSQL-1.0.1.dist-info/METADATA
xPostgreSQL-1.0.1.dist-info/WHEEL
xPostgreSQL-1.0.1.dist-info/top_level.txt
xPostgreSQL-1.0.1.dist-info/RECORD
