Metadata-Version: 2.1
Name: xPostgreSQL
Version: 1.0.1
Summary: A simple library for connecting to PostgreSQL
Author: ks lim
Author-email: kianseng.lim@sony.com
